romeo/__init__.py
romeo/clean.py
romeo/init.py
romeo/logs.py
romeo/romeo.py
romeo/score.py
romeo/train.py
romeo/models/__init__.py
romeo/models/add.py
romeo/models/list.py
romeo/models/models.py
romeo/models/remove.py
romeo/models/tests/__init__.py
romeo/models/tests/test_add.py
romeo/models/tests/test_list.py
romeo/models/tests/test_models.py
romeo/models/tests/test_remove.py
romeo/tests/__init__.py
romeo/tests/test_clean.py
romeo/tests/test_init.py
romeo/tests/test_logs.py
romeo/tests/test_romeo.py
romeo/tests/test_score.py
romeo/tests/test_train.py
romeo-0.1.0.dist-info/AUTHORS.rst
romeo-0.1.0.dist-info/LICENSE
romeo-0.1.0.dist-info/METADATA
romeo-0.1.0.dist-info/WHEEL
romeo-0.1.0.dist-info/entry_points.txt
romeo-0.1.0.dist-info/top_level.txt
romeo-0.1.0.dist-info/RECORD
