Metadata-Version: 2.1
Name: romeo
Version: 0.1.0
Summary: CLI for data science projects
Home-page: https://github.com/brendalf/romeo
Author: Breno Silva
Author-email: brenophp@gmail.com
License: GNU General Public License v3
Keywords: romeo
Platform: UNKNOWN
Classifier: Development Status :: 2 - Pre-Alpha
Classifier: Intended Audience :: Developers
Classifier: License :: OSI Approved :: GNU General Public License v3 (GPLv3)
Classifier: Natural Language :: English
Classifier: Programming Language :: Python :: 3
Classifier: Programming Language :: Python :: 3.5
Classifier: Programming Language :: Python :: 3.6
Classifier: Programming Language :: Python :: 3.7
Classifier: Programming Language :: Python :: 3.8
Requires-Python: >=3.5
Requires-Dist: Click (==7.0)
